daisy_llm/Chat.py
daisy_llm/ChatSpeechProcessor.py
daisy_llm/ConnectionStatus.py
daisy_llm/ContextHandlers.py
daisy_llm/LoadTts.py
daisy_llm/ModuleLoader.py
daisy_llm/SoundManager.py
daisy_llm/Text.py
daisy_llm/__init__.py
daisy_llm/sounds/alert.wav
daisy_llm/sounds/beep.wav
daisy_llm/sounds/end.wav
daisy_llm/sounds/google_tts_test.mp3
daisy_llm/sounds/waiting.wav
daisy_llm-0.0.5.dist-info/METADATA
daisy_llm-0.0.5.dist-info/WHEEL
daisy_llm-0.0.5.dist-info/licenses/LICENSE
daisy_llm-0.0.5.dist-info/RECORD
