Metadata-Version: 2.1
Name: daisy_llm
Version: 0.0.5
Summary: A toolkit for working and conversing with large language models. Featuring tokenized sentence queueing for TTS.
Project-URL: Homepage, https://github.com/myrakrusemark/daisy_llm
Project-URL: Bug Tracker, https://github.com/myrakrusemark/daisy_llm/issues
Author-email: Myra Krusemark <daisy_llm@myrakrusemark.com>
License-File: LICENSE
Classifier: License :: OSI Approved :: MIT License
Classifier: Operating System :: OS Independent
Classifier: Programming Language :: Python :: 3
Requires-Python: >=3.11.1
Requires-Dist: aiohttp
Requires-Dist: aiosignal
Requires-Dist: async-timeout
Requires-Dist: asyncio
Requires-Dist: attrs
Requires-Dist: certifi
Requires-Dist: charset-normalizer
Requires-Dist: click
Requires-Dist: colorama
Requires-Dist: comtypes
Requires-Dist: frozenlist
Requires-Dist: idna
Requires-Dist: joblib
Requires-Dist: multidict
Requires-Dist: nltk
Requires-Dist: numpy
Requires-Dist: openai
Requires-Dist: pyaudio
Requires-Dist: pydub
Requires-Dist: pypiwin32
Requires-Dist: pyttsx3
Requires-Dist: pywin32
Requires-Dist: pyyaml
Requires-Dist: regex
Requires-Dist: requests
Requires-Dist: ruamel-yaml
Requires-Dist: setuptools
Requires-Dist: simpleaudio
Requires-Dist: tqdm
Requires-Dist: urllib3
Requires-Dist: websockets
Requires-Dist: yarl
